src/quantipy/__init__.py
src/quantipy/constants.py
src/quantipy/currency.py
src/quantipy/information.py
src/quantipy/quantity.py
src/quantipy/us.py
miir_quantipy-1.0.0.dist-info/METADATA
miir_quantipy-1.0.0.dist-info/WHEEL
miir_quantipy-1.0.0.dist-info/licenses/LICENSE
miir_quantipy-1.0.0.dist-info/RECORD
