Metadata-Version: 2.1
Name: miir-quantipy
Version: 1.0.0
Summary: a dimensional analysis module
Project-URL: Homepage, https://github.com/itsmiir/qpy
Project-URL: Bug Tracker, https://github.com/itsmiir/qpy/issues
Author-email: miir <itsmiir@outlook.com>
License-File: LICENSE
Classifier: License :: OSI Approved :: MIT License
Classifier: Operating System :: OS Independent
Classifier: Programming Language :: Python :: 3
Requires-Python: >=3.7
